cdk_cloudformation_svectordb_vectordatabase_database/__init__.py
cdk_cloudformation_svectordb_vectordatabase_database/py.typed
cdk_cloudformation_svectordb_vectordatabase_database/_jsii/__init__.py
cdk_cloudformation_svectordb_vectordatabase_database/_jsii/svectordb-vectordatabase-database@1.1.0-alpha.7.jsii.tgz
cdk_cloudformation_svectordb_vectordatabase_database-1.1.0a7.dist-info/LICENSE
cdk_cloudformation_svectordb_vectordatabase_database-1.1.0a7.dist-info/METADATA
cdk_cloudformation_svectordb_vectordatabase_database-1.1.0a7.dist-info/WHEEL
cdk_cloudformation_svectordb_vectordatabase_database-1.1.0a7.dist-info/top_level.txt
cdk_cloudformation_svectordb_vectordatabase_database-1.1.0a7.dist-info/RECORD
